[
  {
    "brand": "Canfield",
    "model": "Nimble 9",
    "year_from": 2020,
    "year_to": 2025,
    "size": "S",
    "frame_material": "Steel",
    "wheel_size": "29/27+"
  },
  {
    "brand": "Canfield",
    "model": "Yelli Screamy",
    "year_from": 2021,
    "year_to": 2025,
    "size": "S",
    "frame_material": "Alloy",
    "wheel_size": "29"
  },
  {
    "brand": "Canfield",
    "model": "ONE.2",
    "year_from": 2021,
    "year_to": 2025,
    "size": "Size 1",
    "frame_material": "Alloy",
    "wheel_size": "29"
  },
  {
    "brand": "Canfield",
    "model": "Tilt",
    "year_from": 2021,
    "year_to": 2025,
    "size": "S",
    "frame_material": "Alloy",
    "wheel_size": "29"
  },
  {
    "brand": "Canfield",
    "model": "Balance",
    "year_from": 2020,
    "year_to": 2022,
    "size": "M",
    "frame_material": "Alloy",
    "wheel_size": "27"
  },
  {
    "brand": "Canfield",
    "model": "Nimble 9",
    "year_from": 2020,
    "year_to": 2025,
    "size": "M",
    "frame_material": "Steel",
    "wheel_size": "29/27+"
  },
  {
    "brand": "Canfield",
    "model": "LITHIUM",
    "year_from": 2021,
    "year_to": 2025,
    "size": "M",
    "frame_material": "Alloy",
    "wheel_size": "29"
  },
  {
    "brand": "Canfield",
    "model": "Tilt",
    "year_from": 2021,
    "year_to": 2025,
    "size": "M",
    "frame_material": "Alloy",
    "wheel_size": "29"
  },
  {
    "brand": "Canfield",
    "model": "Jedi",
    "year_from": 2022,
    "year_to": 2025,
    "size": "M",
    "frame_material": "Alloy",
    "wheel_size": "29"
  },
  {
    "brand": "Canfield",
    "model": "Tilt",
    "year_from": 2021,
    "year_to": 2025,
    "size": "L",
    "frame_material": "Alloy",
    "wheel_size": "29"
  },
  {
    "brand": "Canfield",
    "model": "Yelli Screamy",
    "year_from": 2021,
    "year_to": 2025,
    "size": "L",
    "frame_material": "Alloy",
    "wheel_size": "29"
  },
  {
    "brand": "Canfield",
    "model": "Nimble 9",
    "year_from": 2020,
    "year_to": 2025,
    "size": "L",
    "frame_material": "Steel",
    "wheel_size": "29/27+"
  },
  {
    "brand": "Canfield",
    "model": "LITHIUM",
    "year_from": 2021,
    "year_to": 2025,
    "size": "L",
    "frame_material": "Alloy",
    "wheel_size": "29"
  },
  {
    "brand": "Canfield",
    "model": "Jedi",
    "year_from": 2022,
    "year_to": 2025,
    "size": "L",
    "frame_material": "Alloy",
    "wheel_size": "29"
  },
  {
    "brand": "Canfield",
    "model": "Balance",
    "year_from": 2023,
    "year_to": 2025,
    "size": "L",
    "frame_material": "Alloy",
    "wheel_size": "27"
  },
  {
    "brand": "Canfield",
    "model": "Nimble 9",
    "year_from": 2020,
    "year_to": 2025,
    "size": "XL",
    "frame_material": "Steel",
    "wheel_size": "29/27+"
  },
  {
    "brand": "Canfield",
    "model": "LITHIUM",
    "year_from": 2021,
    "year_to": 2025,
    "size": "XL",
    "frame_material": "Alloy",
    "wheel_size": "29"
  },
  {
    "brand": "Canfield",
    "model": "Jedi",
    "year_from": 2022,
    "year_to": 2025,
    "size": "XL",
    "frame_material": "Alloy",
    "wheel_size": "29"
  },
  {
    "brand": "Canfield",
    "model": "Tilt",
    "year_from": 2021,
    "year_to": 2025,
    "size": "XL",
    "frame_material": "Alloy",
    "wheel_size": "29"
  },
  {
    "brand": "Canfield",
    "model": "Yelli Screamy",
    "year_from": 2021,
    "year_to": 2025,
    "size": "XL",
    "frame_material": "Alloy",
    "wheel_size": "29"
  }
]